marginaleffectsAD/__init__.py
marginaleffectsAD/comparisons.py
marginaleffectsAD/utils.py
marginaleffectsAD/glm/__init__.py
marginaleffectsAD/glm/comparisons.py
marginaleffectsAD/glm/families.py
marginaleffectsAD/glm/predictions.py
marginaleffectsAD/linear/__init__.py
marginaleffectsAD/linear/comparisons.py
marginaleffectsAD/linear/predictions.py
marginaleffectsad-0.0.3.dist-info/licenses/LICENSE.md
marginaleffectsad-0.0.3.dist-info/METADATA
marginaleffectsad-0.0.3.dist-info/WHEEL
marginaleffectsad-0.0.3.dist-info/top_level.txt
marginaleffectsad-0.0.3.dist-info/RECORD
