Metadata-Version: 2.4
Name: marginaleffectsAD
Version: 0.0.3
Summary: Automatic differentiation helpers for the marginaleffects package.
Requires-Python: >=3.11
License-File: LICENSE.md
Requires-Dist: jax>=0.7.1
Requires-Dist: numpy>=2.3.2
Dynamic: license-file
